babylai_auth_client/__init__.py
babylai_auth_client/client.py
babylai_auth_client-0.1.1.dist-info/licenses/LICENSE
babylai_auth_client-0.1.1.dist-info/METADATA
babylai_auth_client-0.1.1.dist-info/WHEEL
babylai_auth_client-0.1.1.dist-info/top_level.txt
babylai_auth_client-0.1.1.dist-info/RECORD
