Metadata-Version: 2.4
Name: babylai-auth-client
Version: 0.1.1
Summary: Python client for BabylAI Auth API (fetch client token)
Author-email: AAU <info@aau.iq>, Ahmed Majid <ahmed1992madrid@gmail.com>
License: MIT
Project-URL: Source, https://github.com/yourusername/babylai_auth_client
Project-URL: Tracker, https://github.com/yourusername/babylai_auth_client/issues
Keywords: babylai,auth,client,token
Classifier: Programming Language :: Python :: 3
Classifier: License :: OSI Approved :: MIT License
Classifier: Operating System :: OS Independent
Requires-Python: >=3.7
License-File: LICENSE
Requires-Dist: requests>=2.25.0
Dynamic: license-file
